streamlit_hierarchy_chart/__init__.py
streamlit_hierarchy_chart/frontend/dist/favicon.ico
streamlit_hierarchy_chart/frontend/dist/index.html
streamlit_hierarchy_chart/frontend/dist/assets/index-BUU0kklO.css
streamlit_hierarchy_chart/frontend/dist/assets/index-OYZhzh48.js
streamlit_hierarchy_chart-0.0.4.dist-info/METADATA
streamlit_hierarchy_chart-0.0.4.dist-info/WHEEL
streamlit_hierarchy_chart-0.0.4.dist-info/top_level.txt
streamlit_hierarchy_chart-0.0.4.dist-info/RECORD
