Metadata-Version: 2.4
Name: streamlit-hierarchy-chart
Version: 0.0.4
Summary: Streamlit component that allows you to create Hierarchy charts
Home-page: 
Author: Winston Ssentongo
Author-email: winstondavid96@gmail.com
Requires-Python: >=3.7
Requires-Dist: streamlit>=0.63
Dynamic: author
Dynamic: author-email
Dynamic: description
Dynamic: description-content-type
Dynamic: requires-dist
Dynamic: requires-python
Dynamic: summary
